py_exp_calc/__init__.py
py_exp_calc/cli_manager.py
py_exp_calc/exp_calc.py
py_exp_calc/main_analysis.py
py_exp_calc/skeleton.py
py_exp_calc/templates/clustering.txt
py_exp_calc-1.1.0.dist-info/LICENSE.txt
py_exp_calc-1.1.0.dist-info/METADATA
py_exp_calc-1.1.0.dist-info/WHEEL
py_exp_calc-1.1.0.dist-info/entry_points.txt
py_exp_calc-1.1.0.dist-info/top_level.txt
py_exp_calc-1.1.0.dist-info/RECORD
