Metadata-Version: 2.1
Name: py_exp_calc
Version: 1.1.0
Summary: Python package for amplifying operations on main Python data structures.
Home-page: https://github.com/seoanezonjic/py_exp_calc
Author: seoanezonjic
Author-email: seoanezonjic@uma.es
License: MIT
Project-URL: Documentation, https://github.com/seoanezonjic/py_exp_calc
Platform: any
Classifier: Development Status :: 4 - Beta
Classifier: Programming Language :: Python
License-File: LICENSE.txt
Requires-Dist: numpy
Requires-Dist: scipy
Requires-Dist: pandas
Requires-Dist: statsmodels
Requires-Dist: py-cmdtabs
Requires-Dist: importlib-metadata ; python_version < "3.8"
Provides-Extra: testing
Requires-Dist: setuptools ; extra == 'testing'
Requires-Dist: pytest ; extra == 'testing'
Requires-Dist: pytest-cov ; extra == 'testing'
